docs/changelog.rst
docs/conf.py
docs/contributing.rst
docs/index.rst
docs/install.rst
docs/requirements.txt
docs/usage.rst
docs/api-src/audb.rst
sphinx_apipages/__init__.py
sphinx_apipages/templates/autosummary/base.rst
sphinx_apipages/templates/autosummary/class.rst
sphinx_apipages/templates/autosummary/function.rst
sphinx_apipages-0.1.3.dist-info/LICENSE
sphinx_apipages-0.1.3.dist-info/METADATA
sphinx_apipages-0.1.3.dist-info/WHEEL
sphinx_apipages-0.1.3.dist-info/top_level.txt
sphinx_apipages-0.1.3.dist-info/RECORD
