Metadata-Version: 2.1
Name: sphinx-apipages
Version: 0.1.3
Summary: Sphinx extension for API documentation with sub-pages
Author-email: Hagen Wierstorf <hwierstorf@audeering.com>
License: MIT License
Project-URL: repository, https://github.com/audeering/sphinx-apipages/
Project-URL: documentation, https://audeering.github.io/audb/
Keywords: documentation,sphinx,autosummary,autodoc,split,api
Classifier: Development Status :: 5 - Production/Stable
Classifier: Intended Audience :: Science/Research
Classifier: Intended Audience :: Developers
Classifier: License :: OSI Approved :: MIT License
Classifier: Operating System :: OS Independent
Classifier: Programming Language :: Python
Classifier: Programming Language :: Python :: 3
Classifier: Programming Language :: Python :: 3.10
Classifier: Topic :: Scientific/Engineering
License-File: LICENSE
Requires-Dist: sphinx
